MANIFEST.in
setup.py
django_walking_settings.egg-info/PKG-INFO
django_walking_settings.egg-info/SOURCES.txt
django_walking_settings.egg-info/dependency_links.txt
django_walking_settings.egg-info/requires.txt
django_walking_settings.egg-info/top_level.txt
tests_module/__init__.py
tests_module/base.py
walking_settings/__init__.py
walking_settings/admin.py
walking_settings/apps.py
walking_settings/core.py
walking_settings/middleware.py
walking_settings/models.py
walking_settings/urls.py
walking_settings/version.py
walking_settings/views.py
walking_settings/migrations/0001_initial.py
walking_settings/migrations/0002_auto_20150805_2337.py
walking_settings/migrations/__init__.py
walking_settings/tests/__init__.py
walking_settings/tests/apps_tests.py
walking_settings/tests/core_tests.py
walking_settings/tests/middleware_tests.py
walking_settings/tests/version_tests.py
walking_settings/tests/views_tests.py