Metadata-Version: 1.1
Name: django-walking-settings
Version: 0.1.1
Summary: a live settings setter for django
Home-page: https://github.com/rfloriano/django-walking-settings
Author: Rafael Floriano da Silva
Author-email: rflorianobr@gmail.com
License: MIT
Keywords: django walking settings live
Platform: UNKNOWN
Classifier: Development Status :: 4 - Beta
Classifier: Intended Audience :: Developers
Classifier: License :: OSI Approved :: MIT License
Classifier: Natural Language :: English
Classifier: Operating System :: Unix
Classifier: Programming Language :: Python :: 2.7
Classifier: Programming Language :: Python :: 3.4
Classifier: Operating System :: OS Independent
